png_zip/__init__.py
png_zip/cli.py
png_zip-0.1.0.dist-info/METADATA
png_zip-0.1.0.dist-info/WHEEL
png_zip-0.1.0.dist-info/entry_points.txt
png_zip-0.1.0.dist-info/licenses/LICENSE
png_zip-0.1.0.dist-info/RECORD
