Metadata-Version: 2.3
Name: png-zip
Version: 0.1.0
Summary: Add your description here
Author-email: ZackaryW <36378555+ZackaryW@users.noreply.github.com>
License-File: LICENSE
Requires-Python: >=3.8
Requires-Dist: click>=8.1.7
